aws_py/__init__.py
aws_py/awspy.py
aws_py/ecs/__init__.py
aws_py/ecs/fargate.py
awspy/__init__.py
awspy/awspy.py
awspy/ecs/__init__.py
awspy/ecs/fargate.py
awspy-1.0.0.dist-info/LICENSE
awspy-1.0.0.dist-info/METADATA
awspy-1.0.0.dist-info/WHEEL
awspy-1.0.0.dist-info/top_level.txt
awspy-1.0.0.dist-info/RECORD
