Metadata-Version: 2.1
Name: awspy
Version: 1.0.0
Summary: Utility tools for running Python services in AWS.
Home-page: https://github.com/ScholarPack/awspy
Author: ScholarPack
Author-email: dev@scholarpack.com
License: UNKNOWN
Platform: UNKNOWN
Classifier: Development Status :: 5 - Production/Stable
Classifier: Programming Language :: Python :: 3
Classifier: License :: OSI Approved :: MIT License
Classifier: Operating System :: OS Independent
Requires-Python: >=3.8
Requires-Dist: requests (>=2.26.0)
Requires-Dist: types-requests (>=2.25.0)
